<?xml version="1.0" encoding="utf-8"?>
<resources>
    <!-- Latin America (Range: 1 to 63) -->
    <ontimcarrier carrier="amxbr"        language="pt-BR" />
    <ontimcarrier carrier="amxpr"        language="es-US" />
    <ontimcarrier carrier="amxmx"        language="es-US" />
    <ontimcarrier carrier="amxcl"        language="es-US" />
    <ontimcarrier carrier="amxar"        language="es-US" />
    <ontimcarrier carrier="amxla"        language="es-US" />
    <ontimcarrier carrier="amxpe"        language="es-US" />
    <ontimcarrier carrier="amxco"        language="es-US" />
    <ontimcarrier carrier="tefbr"        language="pt-BR" />
    <ontimcarrier carrier="tefmx"        language="es-US" />
    <ontimcarrier carrier="tefar"        language="es-US" />
    <ontimcarrier carrier="tefcl"        language="es-US" />
    <ontimcarrier carrier="tefpe"        language="es-US" />
    <ontimcarrier carrier="tefco"        language="es-US" />
    <ontimcarrier carrier="perar"        language="es-US" />
    <ontimcarrier carrier="entcl"        language="es-US" />
    <ontimcarrier carrier="iusmx"        language="es-US" />
    <ontimcarrier carrier="niibr"        language="pt-BR" />
    <ontimcarrier carrier="niicl"        language="es-US" />
    <ontimcarrier carrier="niimx"        language="es-US" />
    <ontimcarrier carrier="niipe"        language="es-US" />
    <ontimcarrier carrier="oibr"         language="pt-BR" />
    <ontimcarrier carrier="timbr"        language="pt-BR" />
    <ontimcarrier carrier="tigco"        language="es-US" />
    <ontimcarrier carrier="retbr"        language="pt-BR" />
    <ontimcarrier carrier="retar"        language="es-US" />
    <ontimcarrier carrier="retla"        language="es-US" />
    <ontimcarrier carrier="retcl"        language="es-US" />
    <ontimcarrier carrier="tefla"        language="es-US" />
    <ontimcarrier carrier="retla1st"     language="es-US" />
    <ontimcarrier carrier="tefunl"       language="es-US" />
    <ontimcarrier carrier="tigca"        language="es-US" />
    <ontimcarrier carrier="tigca1st"     language="es-US" />
    <ontimcarrier carrier="retmx"        language="es-US" />
    <ontimcarrier carrier="attmx"        language="es-US" />
    <ontimcarrier carrier="womcl"        language="es-US" />
    <ontimcarrier carrier="avaco"        language="es-US" />
    <ontimcarrier carrier="retpe"        language="es-US" />
    <ontimcarrier carrier="openla"       language="es-US" />
    <ontimcarrier carrier="opencl"       language="es-US" />
    <ontimcarrier carrier="openmx"       language="es-US" />
    <ontimcarrier carrier="altmx"        language="es-US" />
    <ontimcarrier carrier="openpe"       language="es-US" />
    <!-- Europe, the Middle East and Africa - EMEA (Range: 64 to 127) -->
    <ontimcarrier carrier="reteu"        language="en-US" />
    <ontimcarrier carrier="retgb"        language="en-GB" />
    <ontimcarrier carrier="retfr"        language="fr-FR" />
    <ontimcarrier carrier="retes"        language="es-ES" />
    <ontimcarrier carrier="retie"        language="en-GB" />
    <ontimcarrier carrier="retde"        language="de-DE" />
    <ontimcarrier carrier="vfgb"         language="en-GB" />
    <ontimcarrier carrier="vfde"         language="de-DE" />
    <ontimcarrier carrier="vffr"         language="fr-FR" />
    <ontimcarrier carrier="o2gb"         language="en-GB" />
    <ontimcarrier carrier="o2de"         language="de-DE" />
    <ontimcarrier carrier="orafr"        language="fr-FR" />
    <ontimcarrier carrier="bouyfr"       language="fr-FR" />
    <ontimcarrier carrier="eegb"         language="en-GB" />
    <ontimcarrier carrier="tescogb"      language="en-GB" />
    <ontimcarrier carrier="yoigo"        language="es-ES" />
    <ontimcarrier carrier="oraes"        language="es-ES" />
    <ontimcarrier carrier="retapac"      language="en-US" />
    <ontimcarrier carrier="retmea"       language="en-US" />
    <ontimcarrier carrier="vfit"         language="it-IT" />
    <ontimcarrier carrier="vfes"         language="es-ES" />
    <ontimcarrier carrier="vfeu"         language="en-US" />
    <ontimcarrier carrier="3gb"          language="en-GB" />
    <ontimcarrier carrier="tescoie"      language="en-GB" />
    <ontimcarrier carrier="altfr"        language="fr-FR" />
    <ontimcarrier carrier="3ie"          language="en-GB" />
    <ontimcarrier carrier="altpt"        language="pt-PT" />
    <ontimcarrier carrier="timit"        language="it-IT" />
    <ontimcarrier carrier="retma"        language="ar-MA" />
    <ontimcarrier carrier="windit"       language="it-IT" />
    <ontimcarrier carrier="vfhu"         language="hu-HU" />
    <ontimcarrier carrier="vfro"         language="ro-RO" />
    <ontimcarrier carrier="telhu"        language="hu-HU" />
    <ontimcarrier carrier="playpl"       language="pl-PL" />
    <ontimcarrier carrier="oraeu"        language="en-US" />
    <ontimcarrier carrier="dteu"         language="en-US" />
    <ontimcarrier carrier="teleu"        language="en-US" />
    <ontimcarrier carrier="pluspl"       language="pl-PL" />
    <ontimcarrier carrier="dtpl"         language="pl-PL" />
    <ontimcarrier carrier="tefes"        language="es-ES" />
    <ontimcarrier carrier="altice"       language="en-US" />
    <ontimcarrier carrier="vipeu"        language="en-US" />
    <ontimcarrier carrier="veoneu"       language="en-US" />
    <ontimcarrier carrier="openeu"       language="en-US" />
    <ontimcarrier carrier="reteu2"       language="en-US" />
    <!-- North America (Range: 128 to 191) -->
    <ontimcarrier carrier="retca"        language="en-CA" />
    <ontimcarrier carrier="bwaca"        language="en-CA" />
    <ontimcarrier carrier="tkpca"        language="en-CA" />
    <ontimcarrier carrier="vzw"          language="en-US" />
    <ontimcarrier carrier="att"          language="en-US" />
    <ontimcarrier carrier="tmo"          language="en-US" />
    <ontimcarrier carrier="sprint"       language="en-US" />
    <ontimcarrier carrier="repw"         language="en-US" />
    <ontimcarrier carrier="attpre"       language="en-US" />
    <ontimcarrier carrier="cricket"      language="en-US" />
    <ontimcarrier carrier="cc"           language="en-US" />
    <ontimcarrier carrier="usc"          language="en-US" />
    <ontimcarrier carrier="tracfone"     language="en-US" />
    <ontimcarrier carrier="retus"        language="en-US" />
    <ontimcarrier carrier="metropcs"     language="en-US" />
    <ontimcarrier carrier="rcica"        language="en-CA" />
    <ontimcarrier carrier="wndca"        language="en-CA" />
    <ontimcarrier carrier="dmc"          language="en-US" />
    <ontimcarrier carrier="bby"          language="en-US" />
    <ontimcarrier carrier="amz"          language="en-US" />
    <ontimcarrier carrier="acg"          language="en-US" />
    <ontimcarrier carrier="lra"          language="en-US" />
    <ontimcarrier carrier="comcast"      language="en-US" />
    <ontimcarrier carrier="fi"           language="en-US" />
    <ontimcarrier carrier="vzwpre"       language="en-US" />
    <ontimcarrier carrier="boost"        language="en-US" />
    <ontimcarrier carrier="spectrum"     language="en-US" />
    <!-- Asia and Oceania (Range: 192 to 255) -->
    <ontimcarrier carrier="retin"        language="en-IN" />
    <ontimcarrier carrier="retcn"        language="zh-Hans-CN" />
    <ontimcarrier carrier="telstra"      language="en-AU" />
    <ontimcarrier carrier="vfau"         language="en-AU" />
    <ontimcarrier carrier="amzin"        language="en-IN" />
    <ontimcarrier carrier="jioin"        language="en-IN" />
    <ontimcarrier carrier="airin"        language="en-IN" />
    <ontimcarrier carrier="retid"        language="in-ID" />
    <ontimcarrier carrier="cmcc"         language="zh-Hans-CN" />
    <ontimcarrier carrier="ctcn"         language="zh-Hans-CN" />
    <ontimcarrier carrier="cucn"         language="zh-Hans-CN" />
    <ontimcarrier carrier="retmm"        language="my-MM" />
    <ontimcarrier carrier="gt4gtw"       language="zh-Hant-TW" />
    <ontimcarrier carrier="retth"        language="th-TH" />
    <ontimcarrier carrier="retru"        language="ru-RU" />
    <ontimcarrier carrier="trueth"       language="th-TH" />
    <ontimcarrier carrier="smarthk"      language="zh-Hant-HK" />
    <ontimcarrier carrier="mobilpk"      language="ur-PK" />
    <ontimcarrier carrier="retsea"       language="en-US" />
    <ontimcarrier carrier="retjp"        language="ja-JP" />
    <ontimcarrier carrier="softbank"     language="ja-JP" />
    <ontimcarrier carrier="optus"        language="en-US" />
    <ontimcarrier carrier="retkr"        language="en-US" />
</resources>